<?xml version="1.0" encoding="UTF-8"?>

<!DOCTYPE struts PUBLIC
        "-//Apache Software Foundation//DTD Struts Configuration 2.3//EN"
        "http://struts.apache.org/dtds/struts-2.3.dtd">

<struts>
    <!-- 根目录 / -->
    <package name="root" namespace="/" extends="default">
        <action name="" class="">
            <result name="success" type="redirectAction">home</result>
        </action>
        <action name="home" class="com.free4lab.babycheckup.action.HomeAction">
            <result name="success">index.jsp</result>
            <result name="fail">error.jsp</result>
        </action>
        <action name="record">
            <result>views/babyadmin.jsp</result>
        </action>
        <!--&lt;!&ndash;测试类型判断&ndash;&gt;-->
        <!--<action name="newtest" method="newTestChoice" class="com.free4lab.babycheckup.action.TestAction">-->
            <!--<result name="success" type="redirect">${redirectUrl}?testid=${testid}&amp;babyid=${babyid}</result>-->
        <!--</action>-->
        <!--0-6岁测试-->
        <action name="newtest0_6" method="newTest0_6" class="com.free4lab.babycheckup.action.TestAction">
            <result name="success" >views/newTest1.jsp</result>
            <result name="fail">error.jsp</result>
        </action>

        <!--小儿智能发育筛查测试-->
        <action name="newtestDDST" method="newTestDDST" class="com.free4lab.babycheckup.action.TestAction">
            <result name="success" >views/newTestDDST.jsp</result>
            <result name="fail">error.jsp</result>
        </action>

        <!--3-6岁测试-->
        <action name="newtest3_6" method="newTest3_6" class="com.free4lab.babycheckup.action.TestAction">
            <result name="success" >views/newTest3_6.jsp</result>
            <result name="fail">error.jsp</result>
        </action>
        <!--0-2岁测试-->
        <action name="newtest0_2" method="newTest0_2" class="com.free4lab.babycheckup.action.TestAction">
            <result name="success" >views/newTest0_2.jsp</result>
            <result name="fail">error.jsp</result>
        </action>
        <!--50岁学龄测试-->
        <action name="newtest50" method="newTest50" class="com.free4lab.babycheckup.action.TestAction">
            <result name="success" >views/newTest50.jsp</result>
            <result name="fail">error.jsp</result>
        </action>
        <!--婴幼儿认知能力测试-->
        <action name="newtestcognize" method="newTestCognize" class="com.free4lab.babycheckup.action.TestAction">
            <result name="success" >views/newTestCognize.jsp</result>
            <result name="fail">error.jsp</result>
        </action>
        <!--婴儿-初中学生生活能力量表测试-->
        <action name="newtest132" method="newTest132" class="com.free4lab.babycheckup.action.TestAction">
            <result name="success" >views/newTest132.jsp</result>
            <result name="fail">error.jsp</result>
        </action>
        <!--婴儿-初中学生生活能力量表测试-->
        <action name="newtest0_3" method="newTest0_3" class="com.free4lab.babycheckup.action.TestAction">
            <result name="success" >views/newTest0_3.jsp</result>
            <result name="fail">error.jsp</result>
        </action>
        <!--0-6岁结果-->
        <action name="showreult" method="showResult" class="com.free4lab.babycheckup.action.ResultAction">
            <result name="success" >views/showresult.jsp</result>
        </action>

        <!--3-6岁结果-->
        <action name="showresult3_6" method="showResult3_6" class="com.free4lab.babycheckup.action.ResultAction3_6">
            <result name="success" >views/showresult3_6.jsp</result>
        </action>
        <!--0-2岁结果-->
        <action name="showresult0_2" method="showResult0_2" class="com.free4lab.babycheckup.action.ResultAction0_2">
            <result name="success" >views/showresult0_2.jsp</result>
        </action>
        <!--50结果-->
        <action name="showresult50" method="showResult50" class="com.free4lab.babycheckup.action.ResultAction50">
            <result name="success" >views/showresult50.jsp</result>
        </action>
        <!--婴幼儿认知测定-->
        <action name="showresultcognize" method="showResultCognize" class="com.free4lab.babycheckup.action.ResultCognizeAction">
            <result name="success" >views/showresultCognize.jsp</result>
        </action>
        <!--婴儿-初中学生生活能力量表结果-->
        <action name="showresult132" method="showResult132" class="com.free4lab.babycheckup.action.ResultAction132">
            <result name="success" >views/showresult132.jsp</result>
        </action>

        <!--小儿智能发育筛查-->
        <action name="showresultDDST" method="showResultDDST" class="com.free4lab.babycheckup.action.ResultDDSTAction">
            <result name="success" >views/showresultDDST.jsp</result>
        </action>

        <!--父母育儿0-3结果-->
        <action name="showresult0_3" method="showResult0_3" class="com.free4lab.babycheckup.action.ResultAction0_3">
            <result name="success" >views/showresult0_3.jsp</result>
        </action>

        <action name="saveresult" method="saveResult" class="com.free4lab.babycheckup.action.TestAction">
            <result type="json" name="success">
                <param name="includeProperties">result,result.id</param>
            </result>
            <result name="fail">error.jsp</result>
        </action>
        <!--3-6岁结果-->
        <action name="saveresult3_6" method="saveResult3_6" class="com.free4lab.babycheckup.action.TestAction">
            <result type="json" name="success">
                <param name="includeProperties">result3_6,result3_6.id</param>
            </result>
            <result name="fail">error.jsp</result>
        </action>

        <!--0-2岁结果-->
        <action name="saveresult0_2" method="saveResult0_2" class="com.free4lab.babycheckup.action.TestAction">
            <result type="json" name="success">
                <param name="includeProperties">result0_2,result0_2.id</param>
            </result>
            <result name="fail">error.jsp</result>
        </action>

        <!--0-2岁结果-->
        <action name="saveresult50" method="saveResult50" class="com.free4lab.babycheckup.action.TestAction">
            <result type="json" name="success">
                <param name="includeProperties">result50,result50.id</param>
            </result>
            <result name="fail">error.jsp</result>
        </action>

        <!--婴儿-初中学生生活能力量表结果-->
        <action name="saveresult132" method="saveResult132" class="com.free4lab.babycheckup.action.TestAction">
            <result type="json" name="success">
                <param name="includeProperties">result132,result132.id</param>
            </result>
            <result name="fail">error.jsp</result>
        </action>

        <!--婴幼儿认知测定结果-->
        <action name="saveresultcognize" method="saveResultCognize" class="com.free4lab.babycheckup.action.TestAction">
            <result type="json" name="success">
                <param name="includeProperties">resultCognize,resultCognize.id</param>
            </result>
            <result name="fail">error.jsp</result>
        </action>

        <!--小儿智能发育筛查-->
        <action name="saveresultDDST" method="saveResultDDST" class="com.free4lab.babycheckup.action.TestAction">
            <result type="json" name="success">
                <param name="includeProperties">resultDDST,resultDDST.id</param>
            </result>
            <result name="fail">error.jsp</result>
        </action>

        <!--父母育儿评估量表结果-->
        <action name="saveresult0_3" method="saveResult0_3" class="com.free4lab.babycheckup.action.TestAction">
            <result type="json" name="success">
                <param name="includeProperties">result0_3,result0_3.id</param>
            </result>
            <result name="fail">error.jsp</result>
        </action>

        <!--保存0-6测试评语和测评人-->
        <action name="saverecord" method="saveRecord" class="com.free4lab.babycheckup.action.ResultAction">
            <result type="json" name="success">
                <param name="includeProperties">resultRecord</param>
            </result>
            <result name="fail">error.jsp</result>
        </action>

        <!--保存0_2测试评语和测评人-->
        <action name="saverecord0_2" method="saveRecord0_2" class="com.free4lab.babycheckup.action.ResultAction0_2">
            <result type="json" name="success">
                <param name="includeProperties">resultRecord</param>
            </result>
            <result name="fail">error.jsp</result>
        </action>

        <!--保存0_3测试评语和测评人-->
        <action name="saverecord0_3" method="saveRecord0_3" class="com.free4lab.babycheckup.action.ResultAction0_3">
            <result type="json" name="success">
                <param name="includeProperties">resultRecord</param>
            </result>
            <result name="fail">error.jsp</result>
        </action>

        <!--保存3_6测试评语和测评人-->
        <action name="saverecord3_6" method="saveRecord3_6" class="com.free4lab.babycheckup.action.ResultAction3_6">
            <result type="json" name="success">
                <param name="includeProperties">resultRecord</param>
            </result>
            <result name="fail">error.jsp</result>
        </action>

        <!--保存50测试评语和测评人-->
        <action name="saverecord50" method="saveRecord50" class="com.free4lab.babycheckup.action.ResultAction50">
            <result type="json" name="success">
                <param name="includeProperties">resultRecord</param>
            </result>
            <result name="fail">error.jsp</result>
        </action>

        <!--保存132测试评语和测评人-->
        <action name="saverecord132" method="saveRecord132" class="com.free4lab.babycheckup.action.ResultAction132">
            <result type="json" name="success">
                <param name="includeProperties">resultRecord</param>
            </result>
            <result name="fail">error.jsp</result>
        </action>

        <!--保存cognize测试评语和测评人-->
        <action name="saverecordcognize" method="saveRecordCognize" class="com.free4lab.babycheckup.action.ResultCognizeAction">
            <result type="json" name="success">
                <param name="includeProperties">resultRecord</param>
            </result>
            <result name="fail">error.jsp</result>
        </action>

        <!--保存ddst测试评语和测评人-->
        <action name="saverecordddst" method="saveRecordDDST" class="com.free4lab.babycheckup.action.ResultDDSTAction">
            <result type="json" name="success">
                <param name="includeProperties">resultRecord</param>
            </result>
            <result name="fail">error.jsp</result>
        </action>

        <action name="admin" method="indexAdmin" class="com.free4lab.babycheckup.action.AdminAction">
            <result name="success">views/index_admin.jsp</result>
        </action>
        <action name="useradmin" method="userAdmin" class="com.free4lab.babycheckup.action.AdminAction">
            <result name="success">views/user_admin.jsp</result>
        </action>
        <action name="babyset_admin" method="babySetAdmin" class="com.free4lab.babycheckup.action.AdminAction">
            <result name="success">views/babyset_admin.jsp</result>
        </action>
        <action name="savebabyset" method="saveNewBabySchema" class="com.free4lab.babycheckup.action.AdminAction">
            <result type="json" name="success"> </result>
        </action>
        <action name="baby_admin"  class="">
            <result name="success">views/baby_admin.jsp</result>
        </action>
        <action name="testadmin" method="" class="">
            <result name="success">views/test_admin.jsp</result>
        </action>

        <action name="monthage" method="testMonthage" class="com.free4lab.babycheckup.action.BabyAction">
            <result type="json" name="success">
                <param name="includeProperties">babyid,flag</param>
            </result>
        </action>
        <!--是不是能进行4-7的学龄测试-->
        <action name="monthage50" method="testMonthAge50" class="com.free4lab.babycheckup.action.BabyAction">
            <result type="json" name="success">
                <param name="includeProperties">babyid,flag</param>
            </result>
        </action>
        <!--是不是能进行4-7的学龄测试-->
        <action name="monthageDDST" method="testMonthAgeDDST" class="com.free4lab.babycheckup.action.BabyAction">
            <result type="json" name="success">
                <param name="includeProperties">babyid,flag</param>
            </result>
        </action>
        <!--是不是能进行婴儿-初中学生生活能力量表龄测试-->
        <action name="monthage132" method="testMonthAge132" class="com.free4lab.babycheckup.action.BabyAction">
            <result type="json" name="success">
                <param name="includeProperties">babyid,flag</param>
            </result>
        </action>

        <!--是不是能进行认知测试-->
        <action name="monthagecognize" method="testMonthAgeCognize" class="com.free4lab.babycheckup.action.BabyAction">
            <result type="json" name="success">
                <param name="includeProperties">babyid,flag</param>
            </result>
        </action>

        <action name="findhospital" method="findHospital" class="com.free4lab.babycheckup.action.HospitalAction">
            <result type="json" name="success">
                <param name="includeProperties">name</param>
            </result>
        </action>
        <action name="updatehospital" method="updateHospital" class="com.free4lab.babycheckup.action.HospitalAction">
            <result type="json" name="success">
                <param name="includeProperties">name,flag</param>
            </result>
        </action>

        <action name="isOrderPayed" method="isOrderPayed" class="com.free4lab.babycheckup.action.OrderInfoAction">
            <result type="json" name="success">
                <param name="includeProperties">order,flag</param>
            </result>
        </action>
    </package>
</struts>